Workbook

Sheet README
A1: Supporting_data_v2.xlsx — dữ liệu hỗ trợ FIN_ASSUMPTIONS đã sửa (FinFlow, 29/09/2026)
A3: Quy ước: chữ xanh dương = số gốc nhập từ nguồn; chữ đen = công thức; chữ xanh lá = link sang sheet khác; nền vàng = ô cần team điền/thử.
A4: Mọi mean/std đều là CÔNG THỨC trên dữ liệu gốc → sửa dữ liệu thì kết quả tự cập nhật.
A6: VNIndex_fixed — #10: sửa lỗi ngày, tính lại mean/std, đối chiếu cuối năm với báo chí
A7: Gold_SJC — #12: lợi suất vàng; Bond_10Y — #11; Savings_hist — #9 (chuỗi lịch sử)
A8: Income_growth — #8: std TĂNG TRƯỞNG thu nhập (team đang lấy std của MỨC thu nhập)
A9: CPI_WB — đề xuất tăng chi phí sinh hoạt
A10: Property_CAGR — #3: CAGR theo cửa sổ + kiểm tra nhất quán giá/thuê 30 năm
A11: Nguon_vay_MB_VCB — #1, #1b, #1c, #2
A12: Lai_suat_cho_vay — #6; Gia_thue — #7; Gia_BDS_thi_truong — #3; Tiet_kiem_snapshot — #9 (mẫu điền)
A13: Kenh_dau_tu — bảng tổng hợp mean/std/sampling cho FIN_ASSUMPTIONS và Monte Carlo
A14: LatLong_QA — #13 + công thức bathrooms

Sheet VNIndex_fixed
A1: VN-Index đóng cửa tháng 05/2021–08/2026 (đã sửa lỗi ngày)
A2: Lỗi gốc: 'Mmm-YY' bị Sheets hiểu là Mmm-DD năm 2026 (VD 'May-21' → 21/05/2026) → năm thật nằm ở phần 'ngày'. Block hồi quy G6:O23 của file gốc hỏng do locale (R²=387, số dạng text) → 14,2% cũ không dùng được.
A4: stored_date (giá trị gốc, sai) | B4: Tháng thực | C4: VN-Index đóng cửa | D4: Lợi suất tháng | E4: Log return | G4: Thống kê (công thức) | H4: Giá trị
A5: 2026-05-21 | B5: 2021-05 | C5: 1328.05 | G5: Số lợi suất tháng | H5: =COUNT(D6:D68) -> 63
A6: 2026-06-21 | B6: 2021-06 | C6: 1408.55 | D6: =C6/C5-1 -> 0.060615188 | E6: =LN(C6/C5) -> 0.058849106 | G6: TB lợi suất tháng | H6: =AVERAGE(D6:D68) -> 0.0066587069
A7: 2026-07-21 | B7: 2021-07 | C7: 1310.05 | D7: =C7/C6-1 -> -0.06993007 | E7: =LN(C7/C6) -> -0.072495502 | G7: Std tháng (mẫu) | H7: =STDEV(D6:D68) -> 0.055706198
A8: 2026-08-21 | B8: 2021-08 | C8: 1331.47 | D8: =C8/C7-1 -> 0.016350521 | E8: =LN(C8/C7) -> 0.016218291 | G8: TB năm = TB tháng × 12 | H8: =H6*12 -> 0.079904483
A9: 2026-09-21 | B9: 2021-09 | C9: 1342.06 | D9: =C9/C8-1 -> 0.0079536152 | E9: =LN(C9/C8) -> 0.0079221519 | G9: Std năm = std tháng × √12 | H9: =H7*SQRT(12) -> 0.19297193
A10: 2026-10-21 | B10: 2021-10 | C10: 1444.27 | D10: =C10/C9-1 -> 0.076159039 | E10: =LN(C10/C9) -> 0.073398257 | G10: CAGR | H10: =(C68/C5)^(12/H5)-1 -> 0.063205086
A11: 2026-11-21 | B11: 2021-11 | C11: 1478.44 | D11: =C11/C10-1 -> 0.023659011 | E11: =LN(C11/C10) -> 0.023383474 | G11: TB log return năm | H11: =AVERAGE(E6:E68)*12 -> 0.061288012
A12: 2026-12-21 | B12: 2021-12 | C12: 1498.28 | D12: =C12/C11-1 -> 0.01341955 | E12: =LN(C12/C11) -> 0.013330306
A13: 2026-01-22 | B13: 2022-01 | C13: 1478.96 | D13: =C13/C12-1 -> -0.012894786 | E13: =LN(C13/C12) -> -0.012978645 | G13: Đối chiếu cuối năm | H13: Trong sheet | I13: Báo chí | J13: Chênh | K13: Nguồn
A14: 2026-02-22 | B14: 2022-02 | C14: 1490.13 | D14: =C14/C13-1 -> 0.0075526045 | E14: =LN(C14/C13) -> 0.0075242264 | G14: 2024-12 | H14: =INDEX($C$5:$C$68,MATCH("2024-12",$B$5:$B$68,0)) -> 1266.78 | I14: 1266.78 | J14: =H14-I14 -> 0 | K14: Thanh Niên 31/12/2025: https://thanhnien.vn/vn-index-ket-thuc-nam-2025-voi-muc-tang-khung-gan-41-185251231154434459.htm
A15: 2026-03-22 | B15: 2022-03 | C15: 1492.12 | D15: =C15/C14-1 -> 0.001335454 | E15: =LN(C15/C14) -> 0.001334563 | G15: 2025-12 | H15: =INDEX($C$5:$C$68,MATCH("2025-12",$B$5:$B$68,0)) -> 1784.49 | I15: 1784.49 | J15: =H15-I15 -> 0 | K15: Thanh Niên (như trên); VnEconomy: https://vneconomy.vn/vn-index-chot-2025-o-dinh-cao-lich-su-tang-ky-luc-9-nam.htm
A16: 2026-04-22 | B16: 2022-04 | C16: 1366.8 | D16: =C16/C15-1 -> -0.083987883 | E16: =LN(C16/C15) -> -0.087725686 | G16: Tăng 2025 (sheet) | H16: =H15/H14-1 -> 0.40868185 | I16: 0.4087 | J16: =H16-I16 -> -1.8145219e-05 | K16: VnEconomy: tăng 40,87% so với cuối 2024
A17: 2026-05-22 | B17: 2022-05 | C17: 1292.68 | D17: =C17/C16-1 -> -0.054228856 | E17: =LN(C17/C16) -> -0.055754659
A18: 2026-06-22 | B18: 2022-06 | C18: 1197.6 | D18: =C18/C17-1 -> -0.073552619 | E18: =LN(C18/C17) -> -0.076398029 | G18: Lưu ý: cửa sổ ~5 năm, chỉ số giá (chưa gồm cổ tức); đề xuất lấy mẫu per_year trong Monte Carlo.
A19: 2026-07-22 | B19: 2022-07 | C19: 1206.33 | D19: =C19/C18-1 -> 0.0072895792 | E19: =LN(C19/C18) -> 0.0072631386
A20: 2026-08-22 | B20: 2022-08 | C20: 1280.51 | D20: =C20/C19-1 -> 0.061492295 | E20: =LN(C20/C19) -> 0.059675743
A21: 2026-09-22 | B21: 2022-09 | C21: 1132.11 | D21: =C21/C20-1 -> -0.11589132 | E21: =LN(C21/C20) -> -0.12317529
A22: 2026-10-22 | B22: 2022-10 | C22: 1027.94 | D22: =C22/C21-1 -> -0.092014027 | E22: =LN(C22/C21) -> -0.096526349
A23: 2026-11-22 | B23: 2022-11 | C23: 1048.42 | D23: =C23/C22-1 -> 0.019923342 | E23: =LN(C23/C22) -> 0.019727469
A24: 2026-12-22 | B24: 2022-12 | C24: 1007.09 | D24: =C24/C23-1 -> -0.039421224 | E24: =LN(C24/C23) -> -0.040219285
A25: 2026-01-23 | B25: 2023-01 | C25: 1111.18 | D25: =C25/C24-1 -> 0.1033572 | E25: =LN(C25/C24) -> 0.09835753
A26: 2026-02-23 | B26: 2023-02 | C26: 1024.68 | D26: =C26/C25-1 -> -0.077845174 | E26: =LN(C26/C25) -> -0.081042145
A27: 2026-03-23 | B27: 2023-03 | C27: 1064.64 | D27: =C27/C26-1 -> 0.038997541 | E27: =LN(C27/C26) -> 0.038256345
A28: 2026-04-23 | B28: 2023-04 | C28: 1049.12 | D28: =C28/C27-1 -> -0.014577698 | E28: =LN(C28/C27) -> -0.014684996
A29: 2026-05-23 | B29: 2023-05 | C29: 1075.17 | D29: =C29/C28-1 -> 0.024830334 | E29: =LN(C29/C28) -> 0.024527071
A30: 2026-06-23 | B30: 2023-06 | C30: 1122.18 | D30: =C30/C29-1 -> 0.043723318 | E30: =LN(C30/C29) -> 0.042794433
... A68: 2026-08-26 | B68: 2026-08 | C68: 1832.12 | D68: =C68/C67-1 -> 0.055502425 | E68: =LN(C68/C67) -> 0.054016886

Sheet Gold_SJC
A1: Giá vàng SJC (bán ra, cuối tháng) 01/2016–09/2026
A2: Nguồn: sheet 'Giá vàng SJC' của team (FiinPro). Ô xanh = số gốc; ô đen = công thức.
A4: Ngày | B4: Giá | C4: Lợi suất tháng
A5: 42398 | B5: 32890000 | E5: Số lợi suất tháng | F5: =COUNT(C6:C133) -> 128
A6: 42429 | B6: 33590000 | C6: =B6/B5-1 -> 0.021283065 | E6: TB năm = TB tháng × 12 | F6: =AVERAGE(C6:C133)*12 -> 0.14893449
A7: 42460 | B7: 33340000 | C7: =B7/B6-1 -> -0.0074426913 | E7: Std năm = std tháng × √12 | F7: =STDEV(C6:C133)*SQRT(12) -> 0.14125874
A8: 42489 | B8: 33800000 | C8: =B8/B7-1 -> 0.013797241 | E8: CAGR | F8: =(B133/B5)^(12/F5)-1 -> 0.14877423
A9: 42521 | B9: 33350000 | C9: =B9/B8-1 -> -0.013313609
A10: 42551 | B10: 35220000 | C10: =B10/B9-1 -> 0.056071964 | E10: Tăng giá Dec-to-Dec | F10: Lợi suất
A11: 42580 | B11: 36423000 | C11: =B11/B10-1 -> 0.034156729 | E11: 2017 | F11: =B28/B16-1 -> 0.036616989
A12: 42613 | B12: 36218000 | C12: =B12/B11-1 -> -0.0056283118 | E12: 2018 | F12: =B40/B28-1 -> 0.0028038925
A13: 42643 | B13: 36133000 | C13: =B13/B12-1 -> -0.0023468993 | E13: 2019 | F13: =B52/B40-1 -> 0.16502193
A14: 42674 | B14: 35423000 | C14: =B14/B13-1 -> -0.019649628 | E14: 2020 | F14: =B64/B52-1 -> 0.32
A15: 42704 | B15: 34878000 | C15: =B15/B14-1 -> -0.015385484 | E15: 2021 | F15: =B76/B64-1 -> 0.098930481
A16: 42734 | B16: 35093000 | C16: =B16/B15-1 -> 0.0061643443 | E16: 2022 | F16: =B88/B76-1 -> 0.081914031
A17: 42761 | B17: 35593000 | C17: =B17/B16-1 -> 0.014247856 | E17: 2023 | F17: =B100/B88-1 -> 0.13943028
A18: 42794 | B18: 35903000 | C18: =B18/B17-1 -> 0.0087095777 | E18: 2024 | F18: =B112/B100-1 -> 0.10789474
A19: 42825 | B19: 35583000 | C19: =B19/B18-1 -> -0.0089129042 | E19: 2025 | F19: =B124/B112-1 -> 0.81472684
A20: 42853 | B20: 36023000 | C20: =B20/B19-1 -> 0.012365455 | E20: Std năm (Dec-to-Dec) | F20: =STDEV(F11:F19) -> 0.24881865
A21: 42886 | B21: 35698000 | C21: =B21/B20-1 -> -0.0090220137 | E21: Lưu ý: 2025 tăng bất thường; mean 14,9% là đặc thù giai đoạn — nên chạy độ nhạy.
A22: 42916 | B22: 35618000 | C22: =B22/B21-1 -> -0.0022410219
A23: 42947 | B23: 35713000 | C23: =B23/B22-1 -> 0.0026671907
A24: 42978 | B24: 36193000 | C24: =B24/B23-1 -> 0.013440484
A25: 43007 | B25: 36228000 | C25: =B25/B24-1 -> 0.00096703782
A26: 43039 | B26: 36078000 | C26: =B26/B25-1 -> -0.0041404439
A27: 43069 | B27: 36258000 | C27: =B27/B26-1 -> 0.0049891901
A28: 43098 | B28: 36378000 | C28: =B28/B27-1 -> 0.0033096144
A29: 43131 | B29: 36968000 | C29: =B29/B28-1 -> 0.016218594
A30: 43159 | B30: 36895000 | C30: =B30/B29-1 -> -0.0019746808
A31: 43189 | B31: 36893000 | C31: =B31/B30-1 -> -5.4207887e-05
A32: 43217 | B32: 36730000 | C32: =B32/B31-1 -> -0.0044181823
A33: 43251 | B33: 36740000 | C33: =B33/B32-1 -> 0.00027225701
... A133: 46290 | B133: 144400000 | C133: =B133/B132-1 -> -0.028917283

Sheet Bond_10Y
A1: Lợi suất TPCP Việt Nam 5 năm & 10 năm (cuối năm; 2026 = 25/09)
A2: Nguồn: sheet 'Return Bond' của team (FiinPro). Giả định nắm giữ đến đáo hạn.
A4: Năm | B4: TPCP 5 năm | C4: TPCP 10 năm
A5: 2016 | B5: 0.056 | C5: 0.0638 | E5: TB 10 năm | F5: =AVERAGE(C5:C15) -> 0.040218182
A6: 2017 | B6: 0.0435 | C6: 0.0519 | E6: Std 10 năm | F6: =STDEV(C5:C15) -> 0.013650701
A7: 2018 | B7: 0.0456 | C7: 0.0513 | E7: TB 5 năm | F7: =AVERAGE(B5:B15) -> 0.032272727
A8: 2019 | B8: 0.0203 | C8: 0.0342 | E8: Std 5 năm | F8: =STDEV(B5:B15) -> 0.016385487
A9: 2020 | B9: 0.0121 | C9: 0.0245
A10: 2021 | B10: 0.0088 | C10: 0.0235
A11: 2022 | B11: 0.0493 | C11: 0.0504
A12: 2023 | B12: 0.0172 | C12: 0.0239
A13: 2024 | B13: 0.0244 | C13: 0.0312
A14: 2025 | B14: 0.0339 | C14: 0.0419
A15: 2026 | B15: 0.0439 | C15: 0.0458

Sheet Savings_hist
A1: Lãi suất huy động VND cao nhất thị trường (cuối năm; 2026 = 25/09)
A2: Nguồn: sheet 'Lãi huy động' của team. Dùng mức CAO NHẤT → lệch lên so với lãi suất Big4.
A4: Năm | B4: Kỳ hạn 6–12 tháng | C4: Kỳ hạn >12 tháng
A5: 2016 | B5: 0.065 | C5: 0.072 | E5: TB 6–12 tháng | F5: =AVERAGE(B5:B15) -> 0.065
A6: 2017 | B6: 0.065 | C6: 0.073 | E6: Std 6–12 tháng | F6: =STDEV(B5:B15) -> 0.0081608823
A7: 2018 | B7: 0.065 | C7: 0.073 | E7: TB >12 tháng | F7: =AVERAGE(C5:C15) -> 0.070909091
A8: 2019 | B8: 0.07 | C8: 0.075 | E8: Std >12 tháng | F8: =STDEV(C5:C15) -> 0.0063000721
A9: 2020 | B9: 0.06 | C9: 0.068
A10: 2021 | B10: 0.057 | C10: 0.065
A11: 2022 | B11: 0.076 | C11: 0.074
A12: 2023 | B12: 0.066 | C12: 0.081
A13: 2024 | B13: 0.052 | C13: 0.059
A14: 2025 | B14: 0.059 | C14: 0.064
A15: 2026 | B15: 0.08 | C15: 0.076

Sheet CPI_WB
A1: Lạm phát CPI Việt Nam 2016–2025 (World Bank)
A2: Nguồn: sheet 'Inflation WB' của team. Đề xuất cho living_cost_annual_growth_pct.
A4: Năm | B4: CPI (%/năm)
A5: 2016 | B5: 0.026682482 | E5: TB 2016–2025 | F5: =AVERAGE(B5:B14) -> 0.030920093
A6: 2017 | B6: 0.035202569 | E6: Std | F6: =STDEV(B5:B14) -> 0.0053809923
A7: 2018 | B7: 0.035396281
A8: 2019 | B8: 0.027958237
A9: 2020 | B9: 0.032209344
A10: 2021 | B10: 0.018347155
A11: 2022 | B11: 0.031565075
A12: 2023 | B12: 0.032528928
A13: 2024 | B13: 0.036210927
A14: 2025 | B14: 0.033099931

Sheet Income_growth
A1: Thu nhập bình quân đầu người/tháng (VND) — KSMS 2019–2024
A2: Nguồn: NSO, Khảo sát mức sống dân cư 2024: https://www.nso.gov.vn/wp-content/uploads/2026/03/Sach-Khao-sat-muc-song-dan-cu-2024.pdf
A4: Năm | B4: Thu nhập (VND) | C4: Tăng trưởng
A5: 2019 | B5: 4294500 | E5: TB tăng trưởng (đề xuất mean) | F5: =AVERAGE(C6:C10) -> 0.048697182
A6: 2020 | B6: 4249800 | C6: =B6/B5-1 -> -0.010408662 | E6: Std tăng trưởng (đề xuất std) | F6: =STDEV(C6:C10) -> 0.056814663
A7: 2021 | B7: 4204800 | C7: =B7/B6-1 -> -0.010588734
A8: 2022 | B8: 4672500 | C8: =B8/B7-1 -> 0.11123002 | E8: Cách team đang tính (SAI): std của MỨC thu nhập | F8: =STDEV(B5:B10) -> 482902.35
A9: 2023 | B9: 4961800 | C9: =B9/B8-1 -> 0.061915463 | E9: → đơn vị là VND, không phải % tăng trưởng; không dùng được cho Monte Carlo. n=5, có 2 năm COVID.
A10: 2024 | B10: 5415000 | C10: =B10/B9-1 -> 0.091337821

Sheet Property_CAGR
A1: Giá căn hộ sơ cấp Hà Nội (USD/m²) 2016–2025 và kiểm tra nhất quán giá/thuê (#3)
A2: Nguồn: sheet 'Lạm phát giá mua bds' của team (CafeF + Cushman & Wakefield). Ô vàng = tham số để thử.
A4: Năm | B4: USD/m² | C4: Tăng YoY
A5: 2016 | B5: 1300 | E5: CAGR 2016–2025 | F5: =(B14/B5)^(1/9)-1 -> 0.12657479
A6: 2017 | B6: 1200 | C6: =B6/B5-1 -> -0.076923077 | E6: CAGR 2016–2020 | F6: =(B9/B5)^(1/4)-1 -> 0.036422844
A7: 2018 | B7: 1250 | C7: =B7/B6-1 -> 0.041666667 | E7: CAGR 2020–2025 | F7: =(B14/B9)^(1/5)-1 -> 0.20431049
A8: 2019 | B8: 1400 | C8: =B8/B7-1 -> 0.12 | E8: TB tăng YoY | F8: =AVERAGE(C6:C14) -> 0.13455962
A9: 2020 | B9: 1500 | C9: =B9/B8-1 -> 0.071428571 | E9: Std tăng YoY | F9: =STDEV(C6:C14) -> 0.14299609
A10: 2021 | B10: 1900 | C10: =B10/B9-1 -> 0.26666667
A11: 2022 | B11: 1900 | C11: =B11/B10-1 -> 0 | E11: Mốc neo dài hạn = CPI TB + tăng GDP thực/người
A12: 2023 | B12: 2200 | C12: =B12/B11-1 -> 0.15789474 | E12: CPI TB 2016–2025 (link CPI_WB) | F12: =CPI_WB!F5 -> 0.030920093
A13: 2024 | B13: 3000 | C13: =B13/B12-1 -> 0.36363636 | E13: Tăng GDP thực/người (ước tính — Finance kiểm tra lại từ sheet 'GDP pc') | F13: 0.053
A14: 2025 | B14: 3800 | C14: =B14/B13-1 -> 0.26666667 | E14: Mốc neo | F14: =F12+F13 -> 0.083920093
E16: Kiểm tra nhất quán sau N năm | F16: 19% (PA1 plan) | G16: CAGR 2016–25 | H16: Mốc neo
E17: Tăng giá nhà g | F17: 0.19 | G17: =F5 -> 0.12657479 | H17: =F14 -> 0.083920093
E18: Tăng giá thuê r (plan: 7%) | F18: 0.07 | G18: =F18 -> 0.07 | H18: =F18 -> 0.07
E19: Số năm N | F19: 30 | G19: =F19 -> 30 | H19: =F19 -> 30
E20: Lợi suất cho thuê ban đầu y0 (Vietnambiz: ~3% Q1/2025) | F20: 0.03 | G20: =F20 -> 0.03 | H20: =F20 -> 0.03
E21: Giá nhà nhân lên (lần) | F21: =(1+F17)^F19 -> 184.67531 | G21: =(1+G17)^G19 -> 35.710902 | H21: =(1+H17)^H19 -> 11.218066
E22: Tỷ lệ giá/thuê nhân lên (lần) | F22: =(1+F17)^F19/(1+F18)^F19 -> 24.260263 | G22: =(1+G17)^G19/(1+G18)^G19 -> 4.6912382 | H22: =(1+H17)^H19/(1+H18)^H19 -> 1.4736851
E23: Lợi suất cho thuê ngụ ý sau N năm | F23: =F20*(1+F18)^F19/(1+F17)^F19 -> 0.00123659 | G23: =G20*(1+G18)^G19/(1+G17)^G19 -> 0.0063949002 | H23: =H20*(1+H18)^H19/(1+H17)^H19 -> 0.020357131
E25: Đọc kết quả: g = 19% và r = 7% trong 30 năm → lợi suất cho thuê ~0,1%/năm (không thực tế). Xem docs/KET_QUA_TODO.md #3.

Sheet Nguon_vay_MB_VCB
A1: #1 thời hạn vay MB · #1b tuổi tối đa · #1c phí trả trước hạn · #2 LTV Vietcombank
A2: Mỗi dòng = 1 khẳng định + nguồn. Loại nguồn: Sơ cấp (trang chính thức) / Báo chí / Tổng hợp.
A4: Hạng mục | B4: Nội dung / giá trị | C4: Thời điểm | D4: Loại nguồn | E4: Link | F4: Ghi chú độ tin cậy
A5: #1 MB Dream Home | B5: Vay tới 80%, thời hạn tới 35 năm (mô tả trang sản phẩm MB) | C5: tra cứu 09/2026 | D5: Sơ cấp | E5: https://www.mbbank.com.vn/26/37/113/Chi-tiet/mua-nha-dat-tho-cu-chung-cu-du-an-cho-nguoi-tre-2024-6-5-17-58-30 | F5: Gói riêng cho người trẻ — KHÁC gói CN Vạn Phúc (ân hạn 24 tháng)
A6: #1 MB Dream Home | B6: Dành cho khách hàng 23–40 tuổi | C6: 28/03/2025 | D6: Báo chí (Cổng TTĐT Chính phủ) | E6: https://baochinhphu.vn/mb-tien-phong-ho-tro-nguoi-tre-mua-nha-voi-goi-tin-dung-dream-home-102250328181355734.htm
A7: #1 MB Dream Home | B7: Hạn mức tối đa 5 tỷ; không trả gốc tới 5 năm đầu | C7: 08/2024 | D7: Báo chí | E7: https://thanhnien.vn/gioi-tre-hien-thuc-hoa-giac-mo-an-cu-voi-goi-vay-uu-dai-tu-mb-18524080416314239.htm | F7: Hồ sơ test (vay 5,7 tỷ) vượt hạn mức 5 tỷ → không áp dụng được gói này
A8: #1 MB Dream Home | B8: Ra mắt 03/2024 với thời hạn 30 năm | C8: 03/2024 | D8: Báo chí (VNBA) | E8: https://vnba.org.vn/vi/mb-ra-mat-goi-vay-mua-nha-uu-dai-dac-biet-danh-rieng-cho-khach-tre-13583.htm | F8: Thời hạn đã nâng lên 35 năm sau đó
A9: #1 MB gói khác | B9: Có gói MB cho vay tới 420 tháng | C9: không rõ | D9: Tổng hợp | E9: https://wiki.batdongsan.com.vn/wiki/cac-goi-vay-ngan-hang-mb-bank-809784 | F9: Nguồn tổng hợp — cần MB xác nhận
A10: #1b tuổi tối đa MB | B10: Tuổi khi kết thúc khoản vay ≤ 70 (MB) | C10: không rõ | D10: Tổng hợp | E10: https://thebank.vn/vay-the-chap/cho-vay-mua-can-ho-nha-dat-du-an-ngan-hang-mbbank-40.html | F10: Mâu thuẫn với mốc 75 trong plan → xin MB Vạn Phúc xác nhận
A11: #1b đối chiếu | B11: PVcomBank: từ đủ 18 và không quá 75 tuổi khi kết thúc thời hạn cấp tín dụng | C11: tra cứu 09/2026 | D11: Sơ cấp | E11: https://www.pvcombank.com.vn/tin-tuc/cam-nang-tai-chinh/vay-mua-nha-tra-gop | F11: Mốc 75 có thật nhưng ở ngân hàng khác
A12: #1b đối chiếu | B12: Techcombank: không quá 65 tuổi khi tất toán | C12: tra cứu 09/2026 | D12: Sơ cấp | E12: https://techcombank.com/thong-tin/blog/dieu-kien-vay-the-chap
A13: #1c phí trả trước hạn | B13: Một gói MB: năm 1–2: 2,5%; năm 3: 2%; năm 4: 1,5%; năm 5: 1%; từ năm 6 miễn phí | C13: không rõ | D13: Tổng hợp | E13: https://wiki.batdongsan.com.vn/wiki/lai-suat-ngan-hang-mbbank-evr-803484 | F13: Khác mức phẳng 1% × 5 năm trong to-do → đối chiếu văn bản Vạn Phúc
A14: #2 VCB Nhà Mới Thành Đạt | B14: Khách 20–35 tuổi; vay tối đa 70% giá trị nhà (50% nếu thuê mua); tới 40 năm; miễn trả gốc 5 năm đầu; tối đa 5 tỷ; thả nổi = LS huy động 24 tháng + 3% | C14: 20/05/2025 | D14: Báo chí (CafeF) | E14: https://cafef.vn/lai-suat-cho-vay-mua-nha-tai-vietcombank-vietinbank-agribank-bidv-thap-nhat-bao-nhieu-188250520101155192.chn | F14: Trang sản phẩm: https://www.vietcombank.com.vn/vi-VN/KHCN/SPDV/Vay/Nha-moi-thanh-dat
A15: #2 VCB vay mua nhà dự án | B15: Tối đa 70% nếu thế chấp chính căn nhà định mua; tới 100% nếu thế chấp tài sản khác; tối đa 20 năm | C15: cũ | D15: Tổng hợp | E15: https://banchungcusaigon.com.vn/vay-mua-bat-dong-san-tu-vietcombank.html | F15: Thông tin cũ — LTV phụ thuộc loại tài sản bảo đảm
A16: #2 VCB gói 20.000 tỷ | B16: Thời hạn tới 35 năm; tỷ lệ cho vay có thể tới 100% giá trị BĐS tuỳ hồ sơ | C16: 2025 | D16: Báo chí | E16: https://phapluat.suckhoedoisong.vn/vietcombank-mo-goi-tin-dung-20000-ty-dong-thi-truong-ha-lai-suat-vay-mua-nha-toi-1nam-284865.html | F16: Kết luận: 'LTV 100%' không sai ngân hàng mà là khác sản phẩm/khác TSBĐ
A17: #2 PDF plan trích | B17: 20260729_Thong-bao-lai-suat-2026-thang-6.pdf — theo tên là thông báo LÃI SUẤT | C17: 07/2026 | D17: Sơ cấp | E17: https://www.vietcombank.com.vn/-/media/Project/VCB-Sites/VCB/Tin-tuc/2026/Vietcombank/Vietcombank_202607/Vietcombank_20260721/20260729_Thong-bao-lai-suat-2026-thang-6.pdf | F17: Không mở được trong phiên này; loại văn bản này thường không có LTV → khả năng trích nhầm
A18: #2 VCB lãi suất cơ sở | B18: Thông báo lãi suất cơ sở cho vay trung dài hạn (03/2026) | C18: 16/03/2026 | D18: Sơ cấp | E18: https://www.vietcombank.com.vn/vi-VN/Trang-thong-tin-dien-tu/Articles/2026/03/16/Thong-bao-LSCS-cho-vay-trung-dai-han

Sheet Lai_suat_cho_vay
A1: #6 Mặt bằng lãi suất cho vay (để kiểm tra std 0,75 điểm % của lãi thả nổi)
A2: Mỗi dòng = 1 khẳng định + nguồn. Loại nguồn: Sơ cấp (trang chính thức) / Báo chí / Tổng hợp.
A4: Hạng mục | B4: Nội dung / giá trị | C4: Thời điểm | D4: Loại nguồn | E4: Link | F4: Ghi chú độ tin cậy
A5: LS cho vay mới BQ | B5: 6,96%/năm cuối 2024; giữ quanh 6,96% đến cuối 11/2025 | C5: 11/2025 | D5: Báo chí trích NHNN | E5: https://mekongasean.vn/lai-suat-cho-vay-binh-quan-giu-on-dinh-quanh-muc-696nam-50364.html | F5: Khoản vay MỚI, mọi kỳ hạn — không phải lãi vay mua nhà thả nổi
A6: LS cho vay mới BQ | B6: ~6,34%/năm giữa 04/2025 (giảm 0,6 điểm % so với cuối 2024) | C6: 04/2025 | D6: Báo chí | E6: https://www.dnse.com.vn/senses/tin-tuc/lai-suat-cho-vay-ang-re-ky-luc-35086402
A7: LS cho vay BQ theo quý | B7: Thấp nhất 2020–2022 là 7,9%/năm (quý I/2022) — số liệu FiinPro | C7: 04/2025 | D7: Báo chí | E7: https://www.dnse.com.vn/senses/tin-tuc/lai-suat-cho-vay-ang-re-ky-luc-35086402
A8: LS cho vay BQ (cũ + mới) | B8: 8,1–10,5%/năm (NHTM Nhà nước & cổ phần) | C8: 07/2026 | D8: Báo chí trích NHNN | E8: https://cafef.vn/so-lieu-lai-suat-cho-vay-lai-suat-huy-dong-moi-nhat-cua-he-thong-ngan-hang-188260721204319885.chn | F8: Bao gồm dư nợ cũ → biên rộng do khác sản phẩm, không phải biến động theo thời gian
A9: LS cho vay BQ (cũ + mới) | B9: 8,4–10,7%/năm, tăng 0,2 điểm % so với tháng trước | C9: chưa xác minh ngày | D9: Báo chí | E9: https://vietnamfinance.vn/lai-suat-cho-vay-trung-binh-len-107-nam-thuc-te-khach-vay-cham-dinh-18-d150849.html | F9: Cần kiểm tra ngày đăng trước khi dùng
A10: Kiểm tra std theo thời gian | B10: Std LS huy động >12 tháng (mức cao nhất) 2016–2026 = 0,63 điểm % (sheet Savings_hist) | D10: Tính toán | F10: Lãi thả nổi = LS tham chiếu (thường là LS huy động) + biên → std ~0,6–0,8 ủng hộ 0,75 của plan. Cách (max−min)/4 trên khoảng cắt ngang KHÔNG đúng khái niệm

Sheet Gia_thue
A1: #7 Bằng chứng về tăng giá thuê căn hộ Hà Nội
A2: Mỗi dòng = 1 khẳng định + nguồn. Loại nguồn: Sơ cấp (trang chính thức) / Báo chí / Tổng hợp.
A4: Hạng mục | B4: Nội dung / giá trị | C4: Thời điểm | D4: Loại nguồn | E4: Link | F4: Ghi chú độ tin cậy
A5: Giá thuê vs giá nhà | B5: Giá thuê chung cư ~ổn định quanh 13 triệu/căn trong 3 năm; lợi suất cho thuê giảm từ >4% (Q1/2023) xuống ~3% (Q1/2025); năm 2024 tốc độ tăng giá thuê chỉ ~một nửa tăng giá nhà | C5: 04/2025 | D5: Báo chí (Vietnambiz) | E5: https://vietnambiz.vn/loi-suat-cho-thue-chung-cu-dang-giam-dan-202541323742923.htm | F5: Bằng chứng gần nhất; không ủng hộ 7%/năm nếu giá thuê gần như đi ngang
A6: Giá thuê Q1/2025 | B6: Giá thuê chung cư Hà Nội tăng nhẹ trong quý I/2025 | C6: Q1/2025 | D6: Tổng hợp (Batdongsan) | E6: https://wiki.batdongsan.com.vn/tin-tuc/gia-thue-chung-cu-Ha-Noi-tang-nhe-trong-quy-1-2025-cd-hn-832002
A7: Hiệp hội | B7: VARS: bài về giá thuê căn hộ tăng cao | C7: không rõ | D7: Hiệp hội | E7: https://vars.com.vn/tin-tuc/gia-thue-can-ho-tang-cao-n1897 | F7: Chưa trích được con số cụ thể
A8: Kết luận cho mô hình | B8: Không có chuỗi giá thuê căn hộ thường của Savills/CBRE (chỉ có căn hộ dịch vụ). Nếu giữ 7% thì bắt buộc bật income growth; nếu rent growth > income growth kéo dài 30 năm, RENT tự động mất an toàn cuối kỳ | D8: Phân tích | F8: Xem docs/KET_QUA_TODO.md #7

Sheet Gia_BDS_thi_truong
A1: #3 Bằng chứng thị trường về tăng giá căn hộ Hà Nội
A2: Mỗi dòng = 1 khẳng định + nguồn. Loại nguồn: Sơ cấp (trang chính thức) / Báo chí / Tổng hợp.
A4: Hạng mục | B4: Nội dung / giá trị | C4: Thời điểm | D4: Loại nguồn | E4: Link | F4: Ghi chú độ tin cậy
A5: Savills Q1/2025 | B5: Giá sơ cấp +32% YoY; giá thứ cấp giảm nhẹ lần đầu sau 5 năm | C5: Q1/2025 | D5: Báo cáo chuyên ngành | E5: https://vn.savills.com.vn/research_articles/164027/223536-0 | F5: Tăng nóng tập trung ở sơ cấp
A6: Batdongsan qua Vietnambiz | B6: Giá chung cư Hà Nội +14% năm 2023, +39% năm 2024; 2025 tiếp tục tăng nhưng chậm lại | C6: 10/2025 | D6: Báo chí | E6: https://vietnambiz.vn/nhung-khu-vuc-tang-gia-chung-cu-manh-tai-ha-noi-202510985919392.htm | F6: Giai đoạn 2023–2025 là chu kỳ nóng, không đại diện 30 năm
A7: Dữ liệu của team | B7: CAGR 2016–2025 = 12,66%; 2016–2020 = 3,64%; 2020–2025 = 20,43% (sheet Property_CAGR) | D7: Tính toán | F7: 18–20% chỉ khớp 5 năm gần nhất

Sheet Tiet_kiem_snapshot
A1: #9 Lãi suất tiết kiệm hiện tại theo ngân hàng — MẪU ĐỂ TEAM ĐIỀN từ trang chính thức
A2: Các nguồn báo chí mâu thuẫn nhau → team điền bảng dưới từ biểu lãi suất CHÍNH THỨC của từng ngân hàng (ghi ngày tra cứu + link).
A4: Hạng mục | B4: Nội dung / giá trị | C4: Thời điểm | D4: Loại nguồn | E4: Link | F4: Ghi chú độ tin cậy
A5: Báo chí 02/2026 | B5: Vietcombank: kỳ hạn 12–18 tháng 5,2%; 24 tháng 5,3% | C5: 22/02/2026 | D5: Báo chí (CafeF) | E5: https://cafef.vn/nam-moi-gui-tiet-kiem-tai-agribank-vietcombank-bidv-vietinbank-cao-nhat-bao-nhieu-188260222210249665.chn
A6: Báo chí 03/2026 | B6: Big4 tăng lãi suất: kỳ hạn 12–18 tháng từ 5,2% lên 5,9% | C6: 03/2026 | D6: Báo chí (Znews) | E6: https://znews.vn/vietcombank-vietinbank-bidv-agribank-cung-tang-lai-suat-tiet-kiem-post1638131.html
A7: Báo chí (ngày chưa rõ) | B7: Agribank/BIDV/VCB/VietinBank cùng niêm yết 6,8% kỳ hạn 12 tháng | C7: chưa rõ | D7: Báo chí | E7: https://giadinh.suckhoedoisong.vn/lai-suat-agribank-vietinbank-vietcombank-bidv-moi-nhat-gui-tiet-kiem-400-trieu-dong-vao-agribank-nhan-bao-nhieu-tien | F7: MÂU THUẪN với 2 dòng trên → không dùng khi chưa rõ ngày
A10: Bảng cần điền (ô vàng). Dòng 12 là VÍ DỤ định dạng — xoá khi điền.
A11: Ngân hàng | B11: 6 tháng | C11: 12 tháng | D11: 18 tháng | E11: 24 tháng | F11: Ngày tra cứu | G11: Link biểu lãi suất chính thức
A12: VÍ DỤ: Vietcombank | C12: 0.052 | D12: 0.052 | E12: 0.053 | F12: 22/02/2026 | G12: (ví dụ lấy từ CafeF — thay bằng link vietcombank.com.vn)
A13: Vietcombank
A14: BIDV
A15: VietinBank
A16: Agribank
A17: MB Bank

Sheet Kenh_dau_tu
A1: Tổng hợp 4 kênh đầu tư + độ lệch chuẩn Monte Carlo (giá trị đề xuất, chờ Coordinator + Finance duyệt)
A2: Ô xanh lá = link tới sheet tính toán. Sampling: per_path = rút 1 lần/đường; per_year = rút mỗi năm.
A4: Kênh / biến | B4: Mean (%/năm) | C4: Std (%/năm) | D4: Sampling | E4: Cửa sổ dữ liệu | F4: n | G4: Trạng thái | H4: Lưu ý
A5: Tiết kiệm (6–12 tháng, mức cao nhất) | B5: =Savings_hist!F5 -> 0.065 | C5: =Savings_hist!F6 -> 0.0081608823 | D5: per_path | E5: cuối năm 2016–2026 | F5: 11 | G5: Đề xuất | H5: Lệch lên (mức cao nhất); chờ snapshot #9
A6: Chứng khoán (VN-Index) | B6: =VNIndex_fixed!H8 -> 0.079904483 | C6: =VNIndex_fixed!H9 -> 0.19297193 | D6: per_year | E6: tháng 05/2021–08/2026 | F6: 63 | G6: Đề xuất | H6: Cửa sổ ngắn; chưa gồm cổ tức
A7: Trái phiếu (TPCP 10 năm) | B7: =Bond_10Y!F5 -> 0.040218182 | C7: =Bond_10Y!F6 -> 0.013650701 | D7: per_path | E7: cuối năm 2016–2026 | F7: 11 | G7: Đề xuất | H7: Giữ đến đáo hạn
A8: Vàng (SJC) | B8: =Gold_SJC!F6 -> 0.14893449 | C8: =Gold_SJC!F7 -> 0.14125874 | D8: per_year | E8: tháng 01/2016–09/2026 | F8: 128 | G8: Đề xuất | H8: Giai đoạn tăng bất thường
A9: Tăng thu nhập (NSO) | B9: =Income_growth!F5 -> 0.048697182 | C9: =Income_growth!F6 -> 0.056814663 | D9: per_year | E9: 2019–2024 | F9: 5 | G9: Đề xuất | H9: Biến MỚI — bắt buộc nếu bật rent growth
A10: Tăng chi phí sinh hoạt (CPI) | B10: =CPI_WB!F5 -> 0.030920093 | C10: 0 | D10: — | E10: 2016–2025 | F10: 10 | G10: Đề xuất | H10: Biến MỚI; không random hoá
A11: Lãi thả nổi tham chiếu | C11: 0.0075 | D11: per_path | G11: Đã chốt | H11: Plan B8
A12: Tăng giá BĐS | B12: 0.19 | C12: 0.04 | D12: per_path | G12: Mean chờ #3 | H12: Plan B8; xem Property_CAGR
A13: Tăng giá thuê | B13: 0.07 | C13: 0.0125 | D13: per_path | G13: Mean chờ #7 | H13: Plan B8; xem Gia_thue

Sheet LatLong_QA
A1: #13 QA toạ độ PROJECT_MASTER
A2: 3 dự án Hà Đông trùng hệt toạ độ (20.96069, 105.742059); toạ độ mới từ Google Maps/Places (tra cứu 29/09/2026) — cần team xác minh tòa cụ thể.
A4: project_id | B4: Tên dự án | C4: Lat cũ | D4: Long cũ | E4: Lat mới | F4: Long mới | G4: Lệch (km) | H4: Nguồn toạ độ mới
A5: HD072 | B5: V8 The Vesta | C5: 20.96069 | D5: 105.74206 | E5: 20.945153 | F5: 105.75588 | G5: =2*6371*ASIN(SQRT(SIN(RADIANS(E5-C5)/2)^2+COS(RADIANS(C5))*COS(RADIANS(E5))*SIN(RADIANS(F5-D5)/2)^2)) -> 2.2461166 | H5: Google Maps/Places: 'Toà V8 The Vesta' (Phú Lương)
A6: HD073 | B6: Van Phu Victoria | C6: 20.96069 | D6: 105.74206 | E6: 20.957916 | F6: 105.76916 | G6: =2*6371*ASIN(SQRT(SIN(RADIANS(E6-C6)/2)^2+COS(RADIANS(C6))*COS(RADIANS(E6))*SIN(RADIANS(F6-D6)/2)^2)) -> 2.830849 | H6: Google Maps/Places: 'Toà Văn Phú Victoria' (KĐT Văn Phú); tòa V1 ở 20.9601278, 105.7678317
A7: HD074 | B7: Vinaconex 21 Apartment | C7: 20.96069 | D7: 105.74206 | E7: 20.956777 | F7: 105.75633 | G7: =2*6371*ASIN(SQRT(SIN(RADIANS(E7-C7)/2)^2+COS(RADIANS(C7))*COS(RADIANS(E7))*SIN(RADIANS(F7-D7)/2)^2)) -> 1.5447572 | H7: Google Maps/Places: 'Chung cư Vinaconex 21', 804 Quang Trung
A10: beltway_zone lưu dạng SỐ (cần chuẩn hoá thành chuỗi '4'): 7 dự án
A11: HD062 | B11: Usilk City 103 | C11: 4
A12: HD063 | B12: Usilk City 104 | C12: 4
A13: HD064 | B13: V1 The Terra An Hung | C13: 4
A14: HD065 | B14: V1 The Vesta | C14: 4
A15: HD066 | B15: V3 The Terra An Hung | C15: 4
A16: HD067 | B16: V3 The Vesta | C16: 4
A17: HD068 | B17: V4 The Vesta | C17: 4
A19: Công thức bathrooms (Google Sheets, cột J = bathrooms; CHƯA chạy thử trên Sheet thật):
A20: =ARRAYFORMULA(IF(A2:A="","",IF((TRIM(J2:J)="")+(UPPER(TRIM(J2:J))="N/A"),"Không rõ",J2:J)))
A21: OR() không chạy theo từng phần tử trong ARRAYFORMULA → dùng phép cộng (+). Plan có 2 công thức cho ra 2 nhãn khác nhau → cần chốt 1 nhãn. Hiện có 9 ô 'N/A' dạng text + 4 ô trống.
